tests/__init__.py
tests/test_clean.py
texutil/__init__.py
texutil/scripts/__init__.py
texutil/scripts/txu.py
TeXUtil-0.1.0.dist-info/LICENSE
TeXUtil-0.1.0.dist-info/METADATA
TeXUtil-0.1.0.dist-info/WHEEL
TeXUtil-0.1.0.dist-info/entry_points.txt
TeXUtil-0.1.0.dist-info/top_level.txt
TeXUtil-0.1.0.dist-info/RECORD
