Metadata-Version: 2.1
Name: TeXUtil
Version: 0.1.0
License-File: LICENSE
Requires-Dist: Click
